compress_lightreach-1.0.3.dist-info/licenses/LICENSE
pcompresslr/__init__.py
pcompresslr/_version.py
pcompresslr/api_client.py
pcompresslr/cli.py
pcompresslr/core.py
compress_lightreach-1.0.3.dist-info/METADATA
compress_lightreach-1.0.3.dist-info/WHEEL
compress_lightreach-1.0.3.dist-info/entry_points.txt
compress_lightreach-1.0.3.dist-info/top_level.txt
compress_lightreach-1.0.3.dist-info/RECORD
