Metadata-Version: 2.4
Name: compress-lightreach
Version: 1.0.3
Summary: AI cost management SDK with intelligent model routing, prompt compression, and real-time token tracking
Home-page: https://compress.lightreach.io
Author: Light Reach
Author-email: Light Reach <jonathankt@lightreach.io>
License: MIT
Project-URL: Homepage, https://compress.lightreach.io
Project-URL: Documentation, https://compress.lightreach.io/docs
Project-URL: Source, https://github.com/lightreach/compress-lightreach
Project-URL: Bug Tracker, https://github.com/lightreach/compress-lightreach/issues
Keywords: llm,ai,model-routing,cost-management,compression,token-tracking,openai,anthropic,optimization
Classifier: Development Status :: 4 - Beta
Classifier: Intended Audience :: Developers
Classifier: License :: OSI Approved :: MIT License
Classifier: Programming Language :: Python :: 3
Classifier: Programming Language :: Python :: 3.8
Classifier: Programming Language :: Python :: 3.9
Classifier: Programming Language :: Python :: 3.10
Classifier: Programming Language :: Python :: 3.11
Classifier: Topic :: Software Development :: Libraries :: Python Modules
Classifier: Topic :: Text Processing :: General
Requires-Python: >=3.8
License-File: LICENSE
Requires-Dist: tiktoken>=0.5.0
Requires-Dist: requests>=2.31.0
Requires-Dist: urllib3>=2.0.0
Requires-Dist: python-dotenv>=1.0.0
Requires-Dist: tzdata>=2023.3
Provides-Extra: api
Requires-Dist: fastapi>=0.104.0; extra == "api"
Requires-Dist: uvicorn[standard]>=0.24.0; extra == "api"
Requires-Dist: pydantic>=2.0.0; extra == "api"
Requires-Dist: pydantic-settings>=2.0.0; extra == "api"
Requires-Dist: python-multipart>=0.0.6; extra == "api"
Requires-Dist: slowapi>=0.1.9; extra == "api"
Requires-Dist: httpx>=0.25.0; extra == "api"
Requires-Dist: sqlalchemy>=2.0.0; extra == "api"
Requires-Dist: psycopg2-binary>=2.9.0; extra == "api"
Requires-Dist: bcrypt>=4.0.0; extra == "api"
Requires-Dist: pyjwt>=2.8.0; extra == "api"
Requires-Dist: alembic>=1.12.0; extra == "api"
Requires-Dist: stripe>=7.0.0; extra == "api"
Requires-Dist: cryptography>=42.0.0; extra == "api"
Dynamic: author
Dynamic: home-page
Dynamic: license-file
Dynamic: requires-python
